allpairspy/__init__.py
allpairspy/__version__.py
allpairspy/allpairs.py
allpairspy/pairs_storage.py
allpairspy-2.5.1.dist-info/LICENSE.txt
allpairspy-2.5.1.dist-info/METADATA
allpairspy-2.5.1.dist-info/WHEEL
allpairspy-2.5.1.dist-info/top_level.txt
allpairspy-2.5.1.dist-info/RECORD
